newsed/.DS_Store
newsed/__init__.py
newsed/app.py
newsed-0.6.0.dist-info/LICENSE
newsed-0.6.0.dist-info/METADATA
newsed-0.6.0.dist-info/WHEEL
newsed-0.6.0.dist-info/entry_points.txt
newsed-0.6.0.dist-info/RECORD
