Metadata-Version: 2.1
Name: newsed
Version: 0.6.0
Summary: A package to fetch and display news articles.
Author: avycado13
Author-email: 108358183+avycado13@users.noreply.github.com
Requires-Python: >=3.8,<4.0
Classifier: Programming Language :: Python :: 3
Classifier: Programming Language :: Python :: 3.8
Classifier: Programming Language :: Python :: 3.9
Classifier: Programming Language :: Python :: 3.10
Classifier: Programming Language :: Python :: 3.11
Classifier: Programming Language :: Python :: 3.12
Requires-Dist: beautifulsoup4 (>=4.9.3,<5.0.0)
Requires-Dist: blessed (>=1.17.12,<2.0.0)
Requires-Dist: feedparser (>=6.0.11,<7.0.0)
Requires-Dist: requests (>=2.25.1,<3.0.0)
